networkaddress/__init__.py
networkaddress/macaddress.py
networkaddress/portnumber.py
networkaddress/py.typed
networkaddress-0.0.2.dist-info/LICENSE
networkaddress-0.0.2.dist-info/METADATA
networkaddress-0.0.2.dist-info/WHEEL
networkaddress-0.0.2.dist-info/top_level.txt
networkaddress-0.0.2.dist-info/RECORD
