Metadata-Version: 2.1
Name: networkaddress
Version: 0.0.2
Summary: A network address manipulation library
Author-email: "Duy N. H. A." <me@duynha.dev>
License: MIT License
Project-URL: homepage, https://github.com/duynhaaa/networkaddress
Project-URL: repository, https://github.com/duynhaaa/networkaddress
Keywords: Networking
Classifier: Development Status :: 1 - Planning
Classifier: Intended Audience :: Developers
Classifier: Intended Audience :: Education
Classifier: Intended Audience :: Information Technology
Classifier: Intended Audience :: Manufacturing
Classifier: Intended Audience :: System Administrators
Classifier: Intended Audience :: Science/Research
Classifier: Intended Audience :: Telecommunications Industry
Classifier: Programming Language :: Python
Classifier: Programming Language :: Python :: 3
Classifier: Programming Language :: Python :: 3 :: Only
Classifier: Programming Language :: Python :: 3.9
Classifier: Programming Language :: Python :: 3.10
Classifier: Programming Language :: Python :: 3.11
Classifier: Programming Language :: Python :: 3.12
Classifier: Operating System :: OS Independent
Classifier: License :: OSI Approved :: MIT License
Classifier: Topic :: Documentation
Classifier: Topic :: Documentation :: Sphinx
Classifier: Topic :: Internet
Classifier: Topic :: Software Development
Classifier: Topic :: Software Development :: Libraries
Classifier: Topic :: System
Classifier: Topic :: System :: Hardware
Classifier: Topic :: System :: Networking
Classifier: Topic :: Utilities
Classifier: Typing :: Typed
Requires-Python: >=3.9
License-File: LICENSE
Provides-Extra: build
Requires-Dist: build ; extra == 'build'
Provides-Extra: develop
Requires-Dist: networkaddress[lint] ; extra == 'develop'
Requires-Dist: networkaddress[test] ; extra == 'develop'
Requires-Dist: networkaddress[build] ; extra == 'develop'
Requires-Dist: networkaddress[publish] ; extra == 'develop'
Provides-Extra: lint
Requires-Dist: flake8 ; extra == 'lint'
Requires-Dist: flake8-pyproject ; extra == 'lint'
Requires-Dist: isort ; extra == 'lint'
Requires-Dist: mypy ; extra == 'lint'
Requires-Dist: pylint ; extra == 'lint'
Requires-Dist: pycodestyle ; extra == 'lint'
Provides-Extra: publish
Requires-Dist: twine ; extra == 'publish'
Provides-Extra: test
Requires-Dist: pytest ; extra == 'test'
Requires-Dist: pytest-cov ; extra == 'test'
